sqlalchemy_media/__init__.py
sqlalchemy_media/constants.py
sqlalchemy_media/context.py
sqlalchemy_media/exceptions.py
sqlalchemy_media/helpers.py
sqlalchemy_media/typing.py
sqlalchemy_media/attachments/__init__.py
sqlalchemy_media/attachments/attachment.py
sqlalchemy_media/attachments/collections.py
sqlalchemy_media/attachments/file.py
sqlalchemy_media/attachments/image.py
sqlalchemy_media/stores/__init__.py
sqlalchemy_media/stores/base.py
sqlalchemy_media/stores/exceptions.py
sqlalchemy_media/stores/filesystem.py
sqlalchemy_media/stores/manager.py
sqlalchemy_media/tests/__init__.py
sqlalchemy_media/tests/helpers.py
sqlalchemy_media/tests/test_collections.py
sqlalchemy_media/tests/test_delete_orphan.py
sqlalchemy_media/tests/test_file.py
sqlalchemy_media/tests/test_filesystem_store.py
sqlalchemy_media/tests/test_helpers.py
sqlalchemy_media/tests/test_store_context.py
sqlalchemy_media-0.1.0.dev3.dist-info/DESCRIPTION.rst
sqlalchemy_media-0.1.0.dev3.dist-info/METADATA
sqlalchemy_media-0.1.0.dev3.dist-info/RECORD
sqlalchemy_media-0.1.0.dev3.dist-info/WHEEL
sqlalchemy_media-0.1.0.dev3.dist-info/metadata.json
sqlalchemy_media-0.1.0.dev3.dist-info/top_level.txt
