Metadata-Version: 2.0
Name: sqlalchemy-media
Version: 0.1.0.dev3
Summary: Sqlalchemy asset manager
Home-page: http://sqlalchemy-media.dobisel.com
Author: Vahid Mardani
Author-email: vahid.mardani@gmail.com
License: UNKNOWN
Platform: any
Classifier: Programming Language :: Python :: 3.5
Classifier: Topic :: Software Development :: Libraries
Requires-Dist: sqlalchemy (>=1.1.0b3)
